eliteprospect/__init__.py
eliteprospect/eliteprospect_scraper.py
eliteprospect_scraper-1.2.dist-info/METADATA
eliteprospect_scraper-1.2.dist-info/WHEEL
eliteprospect_scraper-1.2.dist-info/top_level.txt
eliteprospect_scraper-1.2.dist-info/RECORD
