Metadata-Version: 2.1
Name: eliteprospect_scraper
Version: 1.2
Summary: Functions to scrape ice hockey data from eliteprospects
Home-page: https://github.com/msjoelin/eliteprospect_scraper
Download-URL: https://pypi.org/project/eliteprospect_scraper/
Author: Marcus Sjölin
Author-email: marcussjolin89@gmail.com
License: MIT
Keywords: ice hockey,scraping,sport analytics,eliteprospects
Requires-Dist: numpy
Requires-Dist: pandas
Requires-Dist: bs4
Requires-Dist: datetime
Requires-Dist: selenium
Requires-Dist: requests
